djpymemcache/__init__.py
djpymemcache/backend.py
djpymemcache/client.py
tests/__init__.py
tests/models.py
tests/settings.py
tests/test_cache.py
tests/test_sessions.py
django_pymemcache-1.0.0.dist-info/LICENSE
django_pymemcache-1.0.0.dist-info/METADATA
django_pymemcache-1.0.0.dist-info/WHEEL
django_pymemcache-1.0.0.dist-info/top_level.txt
django_pymemcache-1.0.0.dist-info/RECORD
