Metadata-Version: 1.1
Name: django-pymemcache
Version: 1.0.0
Summary: Django cache backend based on Pinterest's pymemcache client.
Home-page: https://github.com/django-pymemcache/django-pymemcache
Author: James Socol
Author-email: me@jamessocol.com
License: Apache Software License 2.0
Platform: UNKNOWN
Classifier: Development Status :: 5 - Production/Stable
Classifier: Environment :: Web Environment
Classifier: Intended Audience :: Developers
Classifier: Framework :: Django :: 2.2
Classifier: Framework :: Django :: 3.0
Classifier: License :: OSI Approved :: Apache Software License
Classifier: Operating System :: OS Independent
Classifier: Programming Language :: Python :: 3
Classifier: Programming Language :: Python :: 3.6
Classifier: Programming Language :: Python :: 3.7
Classifier: Programming Language :: Python :: 3.8
Classifier: Topic :: Software Development :: Libraries :: Python Modules
